img2fig/__init__.py
img2fig/img2fig.py
markdown_img2fig-1.0.1.dist-info/LICENSE
markdown_img2fig-1.0.1.dist-info/METADATA
markdown_img2fig-1.0.1.dist-info/WHEEL
markdown_img2fig-1.0.1.dist-info/top_level.txt
markdown_img2fig-1.0.1.dist-info/RECORD
