Metadata-Version: 2.1
Name: markdown-img2fig
Version: 1.0.1
Summary: Convert markdown imgs into captioned <figure>s
Home-page: https://github.com/zetaloop/markdown_img2fig
Author: zetaloop
Author-email: zetaloop@outlook.com
License: MIT
Keywords: markdown img figure caption
Classifier: Development Status :: 4 - Beta
Classifier: Intended Audience :: Developers
Classifier: Topic :: Text Processing :: Markup :: HTML
Classifier: License :: OSI Approved :: MIT License
Classifier: Programming Language :: Python :: 3
Classifier: Operating System :: OS Independent
Requires-Python: >=3.8
License-File: LICENSE
Requires-Dist: Markdown>=3.0.1
